{
  "meta": {
    "title": "Task Dashboard",
    "updatedAt": "2026-02-20T11:56:03Z",
    "source": "Dictation Router + OpenClaw supervisor",
    "uiTemplateVersion": "a9dbebebb8a6da7e"
  },
  "summary": {
    "totalTasks": 6,
    "queued": 1,
    "active": 0,
    "completed": 3,
    "due": 2,
    "blocked": 2,
    "executedTotal": 10,
    "byStatus": {
      "queued": 1,
      "completed": 3,
      "failed": 2
    }
  },
  "laneMetrics": {
    "execution": {
      "visible": 0,
      "executedTotal": 10
    },
    "queue": {
      "visible": 1,
      "totalQueued": 1
    },
    "completed": {
      "visible": 3,
      "totalClosed": 3
    },
    "due": {
      "visible": 2,
      "reviewRequired": 0,
      "failed": 2,
      "blocked": 0,
      "needsInput": 0
    }
  },
  "execution": [],
  "queueTop": [
    {
      "id": "inbox-2230",
      "title": "Design learning for decision quality, not completion rates",
      "source": "dictation-router",
      "priority": "high",
      "status": "queued",
      "sequence": 1,
      "createdAt": "2026-02-14T13:45:49Z",
      "updatedAt": "2026-02-20T11:56:03Z",
      "completedAt": null,
      "ageHours": 142.17,
      "deliverySummary": "Action: create_task | Route: direct | Detail: Waiting for OpenClaw execution",
      "deliverableUrl": null,
      "notes": [
        "capture_id=747",
        "inbox_item_id=2230"
      ],
      "action": "create_task",
      "scope": "professional",
      "hasDeliverable": false,
      "needsReview": false
    }
  ],
  "userActionsDue": [
    {
      "id": "openclaw-1612",
      "title": "Design learning for decision quality, not completion rates",
      "source": "openclaw",
      "priority": "medium",
      "status": "failed",
      "sequence": 0,
      "createdAt": "2026-02-20T11:55:39Z",
      "updatedAt": "2026-02-20T11:56:03Z",
      "completedAt": "2026-02-20T11:56:03Z",
      "ageHours": 0.01,
      "deliverySummary": "Rewrite required before publish. Violations: duplicate title against published post",
      "deliverableUrl": "/ops/deliverables/openclaw-1612.md",
      "notes": [
        "Publish quality gate failed."
      ],
      "scope": "professional",
      "hasDeliverable": true,
      "needsReview": false
    },
    {
      "id": "openclaw-1609",
      "title": "Learning transfer field note for workplace teams 20260220",
      "source": "openclaw",
      "priority": "medium",
      "status": "failed",
      "sequence": 0,
      "createdAt": "2026-02-20T11:52:14Z",
      "updatedAt": "2026-02-20T11:52:25Z",
      "completedAt": "2026-02-20T11:52:25Z",
      "ageHours": 0.07,
      "deliverySummary": "Check OPENCLAW_SSH_HOST and OpenClaw runtime on Mac mini.",
      "deliverableUrl": "/ops/deliverables/openclaw-1609.md",
      "notes": [
        "OpenClaw SSH execution failed."
      ],
      "scope": "professional",
      "hasDeliverable": true,
      "needsReview": false
    }
  ],
  "completedRecent": [
    {
      "id": "openclaw-1603",
      "title": "Improve judgment without adding course fatigue",
      "source": "openclaw",
      "priority": "medium",
      "status": "completed",
      "sequence": 0,
      "createdAt": "2026-02-20T11:43:36Z",
      "updatedAt": "2026-02-20T11:43:59Z",
      "completedAt": "2026-02-20T11:43:59Z",
      "ageHours": 0.21,
      "deliverySummary": "",
      "deliverableUrl": "/ops/deliverables/openclaw-1603.md",
      "notes": [],
      "scope": "professional",
      "hasDeliverable": true,
      "needsReview": false
    },
    {
      "id": "openclaw-1593",
      "title": "Autonomous writing sprint: Turn training requests into measurable capability outcomes",
      "source": "openclaw",
      "priority": "medium",
      "status": "completed",
      "sequence": 0,
      "createdAt": "2026-02-20T10:12:23Z",
      "updatedAt": "2026-02-20T10:12:31Z",
      "completedAt": "2026-02-20T10:12:31Z",
      "ageHours": 1.73,
      "deliverySummary": "",
      "deliverableUrl": "/ops/deliverables/openclaw-1593.md",
      "notes": [],
      "scope": "professional",
      "hasDeliverable": true,
      "needsReview": false
    },
    {
      "id": "openclaw-1588",
      "title": "Use this exact article title: Use reflective debriefs after projects to strengthen learning t...",
      "source": "openclaw",
      "priority": "medium",
      "status": "completed",
      "sequence": 0,
      "createdAt": "2026-02-20T09:59:02Z",
      "updatedAt": "2026-02-19T09:59:50Z",
      "completedAt": "2026-02-19T09:59:50Z",
      "ageHours": 1.95,
      "deliverySummary": "",
      "deliverableUrl": "/ops/deliverables/openclaw-1588.md",
      "notes": [],
      "scope": "professional",
      "hasDeliverable": true,
      "needsReview": false
    }
  ],
  "observations": [
    {
      "level": "info",
      "message": "Autonomous mode is active: review gates are bypassed and blocked/failed tasks follow retry-with-cooldown before final close."
    },
    {
      "level": "info",
      "message": "Blog autopilot is active: non-autonomous tasks are prioritized first; one new blog run is auto-seeded whenever idle with ~5 min break (12/day)."
    },
    {
      "level": "info",
      "message": "Blog publish automation is active: completed blog deliverables are converted to post payloads and pushed via publish_pipeline."
    },
    {
      "level": "info",
      "message": "Queue has 1 task(s). OpenClaw will continue dispatching sequentially while idle."
    },
    {
      "level": "warn",
      "message": "'Tasks due from you' has 2 item(s): failed=2."
    }
  ],
  "errors": [
    {
      "source": "openclaw",
      "timestamp": "2026-02-20T11:56:03Z",
      "message": "Publish quality gate failed."
    },
    {
      "source": "openclaw",
      "timestamp": "2026-02-20T11:54:39Z",
      "message": "Publish quality gate failed."
    },
    {
      "source": "openclaw",
      "timestamp": "2026-02-20T11:53:12Z",
      "message": "Publish quality gate failed."
    },
    {
      "source": "openclaw",
      "timestamp": "2026-02-20T11:52:25Z",
      "message": "OpenClaw SSH execution failed."
    },
    {
      "source": "openclaw",
      "timestamp": "2026-02-20T11:51:14Z",
      "message": "Publish quality gate failed."
    },
    {
      "source": "openclaw",
      "timestamp": "2026-02-20T11:49:48Z",
      "message": "Publish quality gate failed."
    },
    {
      "source": "openclaw",
      "timestamp": "2026-02-18T09:53:57Z",
      "message": "GitHub Pages external indexing in progress. Live URL returns 301 until deployment completes (typically 1-2 minutes)."
    },
    {
      "source": "openclaw",
      "timestamp": "2026-02-18T09:51:35Z",
      "message": "GitHub Pages deployment in progress. Live URL returns 301 to 'Page not found'. Sitemap.xml and RSS need rebuild cycle."
    }
  ],
  "recentActivity": [
    {
      "timestamp": "2026-02-20T11:56:03Z",
      "type": "executed",
      "taskId": "capture-649",
      "message": "Design learning for decision quality, not completion rates: Delegated via OpenClaw SSH (status=completed, task_id=33368a08-6df4-4242-8130-5d7cf7ca79f1): Context overflow: prompt too large for the model. Try /reset (or /new) to start a fresh session, or use a larger-context model."
    },
    {
      "timestamp": "2026-02-20T11:54:38Z",
      "type": "executed",
      "taskId": "capture-647",
      "message": "Design learning for decision quality, not completion rates: Delegated via OpenClaw SSH (status=completed, task_id=3f975166-6386-4be3-9d84-4f431fba3383): Context overflow: prompt too large for the model. Try /reset (or /new) to start a fresh session, or use a larger-context model."
    },
    {
      "timestamp": "2026-02-20T11:53:12Z",
      "type": "executed",
      "taskId": "capture-645",
      "message": "Design learning for decision quality, not completion rates: Delegated via OpenClaw SSH (status=completed, task_id=556e107f-8117-4986-b2f2-d4f73c97c68e): Context overflow: prompt too large for the model. Try /reset (or /new) to start a fresh session, or use a larger-context model."
    },
    {
      "timestamp": "2026-02-20T11:52:25Z",
      "type": "skipped",
      "taskId": "capture-644",
      "message": "Learning transfer field note for workplace teams 20260220: OpenClaw SSH execution failed: OpenClaw SSH command failed: return code 255"
    },
    {
      "timestamp": "2026-02-20T11:51:13Z",
      "type": "executed",
      "taskId": "capture-643",
      "message": "Learning transfer field note for workplace teams 20260220: Delegated via OpenClaw SSH (status=completed, task_id=2a17c6ad-0d4d-463a-80ed-cfef036735a6): Context overflow: prompt too large for the model. Try /reset (or /new) to start a fresh session, or use a larger-context model."
    },
    {
      "timestamp": "2026-02-20T11:49:48Z",
      "type": "executed",
      "taskId": "capture-648",
      "message": "Learning transfer field note for workplace teams 20260220: Delegated via OpenClaw SSH (status=completed, task_id=2bfaab24-489d-433f-a27f-1bc11f5d7b18): Context overflow: prompt too large for the model. Try /reset (or /new) to start a fresh session, or use a larger-context model."
    },
    {
      "timestamp": "2026-02-20T11:48:26Z",
      "type": "executed",
      "taskId": "capture-747",
      "message": "Learning transfer field note for workplace teams 20260220: Delegated via OpenClaw SSH (status=completed, task_id=cac4f770-eb78-450f-a1f0-10b550bce1c6): Context overflow: prompt too large for the model. Try /reset (or /new) to start a fresh session, or use a larger-context model."
    },
    {
      "timestamp": "2026-02-20T11:47:09Z",
      "type": "executed",
      "taskId": "capture-835",
      "message": "Learning transfer field note for workplace teams 20260220: Delegated via OpenClaw SSH (status=completed, task_id=bea85246-1a2b-4473-be31-d37798c24964): Context overflow: prompt too large for the model. Try /reset (or /new) to start a fresh session, or use a larger-context model."
    },
    {
      "timestamp": "2026-02-20T11:45:54Z",
      "type": "executed",
      "taskId": "capture-944",
      "message": "Learning transfer field note for workplace teams 20260220: Delegated via OpenClaw SSH (status=completed, task_id=770668fb-c0c9-4c2b-aa77-db9586fb0963): Context overflow: prompt too large for the model. Try /reset (or /new) to start a fresh session, or use a larger-context model."
    },
    {
      "timestamp": "2026-02-20T11:43:59Z",
      "type": "executed",
      "taskId": "capture-1058",
      "message": "Use scenario based practice to improve judgment without adding course fatigue: Delegated via OpenClaw SSH (status=completed, task_id=a5005cc8-67a8-4d1f-9bb3-2c051ecc3701): Context overflow: prompt too large for the model. Try /reset (or /new) to start a fresh session, or use a larger-context model."
    },
    {
      "timestamp": "2026-02-20T11:43:19Z",
      "type": "executed",
      "taskId": "capture-1057",
      "message": "Create L&D reviews that focus on behavior shifts not completion dashboards: Delegated via OpenClaw SSH (status=completed, task_id=3bbf67b4-a7fe-4383-a6e5-2c6cca1858d7): Context overflow: prompt too large for the model. Try /reset (or /new) to start a fresh session, or use a larger-context model."
    },
    {
      "timestamp": "2026-02-20T11:42:11Z",
      "type": "executed",
      "taskId": "capture-1056",
      "message": "Use reflective debriefs after projects to strengthen learning transfer: Delegated via OpenClaw SSH (status=completed, task_id=6d18fd64-cd63-42b6-ab12-fc10f252c8b9): Context overflow: prompt too large for the model. Try /reset (or /new) to start a fresh session, or use a larger-context model."
    },
    {
      "timestamp": "2026-02-20T10:20:56Z",
      "type": "executed",
      "taskId": "capture-1082",
      "message": "Autonomous writing sprint: Coach managers to run better learning conversations in weekly one...: Delegated via OpenClaw SSH (status=completed, task_id=7d996954-f92a-4690-a2cf-ac3a0fc63f61): Context overflow: prompt too large for the model. Try /reset (or /new) to start a fresh session, or use a larger-context model."
    },
    {
      "timestamp": "2026-02-20T10:20:41Z",
      "type": "executed",
      "taskId": "capture-1082",
      "message": "Autonomous writing sprint: Coach managers to run better learning conversations in weekly one on ones: Autonomous blog task seeded and queued for OpenClaw."
    },
    {
      "timestamp": "2026-02-20T10:19:41Z",
      "type": "executed",
      "taskId": "capture-1081",
      "message": "Autonomous writing sprint: Turn training requests into measurable capability outcomes: Delegated via OpenClaw SSH (status=completed, task_id=96f18563-effa-4c3e-90d5-3ae2992d7c59): Context overflow: prompt too large for the model. Try /reset (or /new) to start a fresh session, or use a larger-context model."
    },
    {
      "timestamp": "2026-02-20T10:19:22Z",
      "type": "executed",
      "taskId": "capture-1081",
      "message": "Autonomous writing sprint: Turn training requests into measurable capability outcomes: Autonomous blog task seeded and queued for OpenClaw."
    },
    {
      "timestamp": "2026-02-20T10:18:23Z",
      "type": "executed",
      "taskId": "capture-1080",
      "message": "Autonomous writing sprint: Turn training requests into measurable capability outcomes: Delegated via OpenClaw SSH (status=completed, task_id=d87db525-04cc-417b-8d2e-c40fc4bbe212): Context overflow: prompt too large for the model. Try /reset (or /new) to start a fresh session, or use a larger-context model."
    },
    {
      "timestamp": "2026-02-20T10:18:02Z",
      "type": "executed",
      "taskId": "capture-1080",
      "message": "Autonomous writing sprint: Turn training requests into measurable capability outcomes: Autonomous blog task seeded and queued for OpenClaw."
    },
    {
      "timestamp": "2026-02-20T10:17:01Z",
      "type": "executed",
      "taskId": "capture-1079",
      "message": "Autonomous writing sprint: Turn training requests into measurable capability outcomes: Delegated via OpenClaw SSH (status=completed, task_id=9cad68da-075d-4cd8-99e2-69cbe39713aa): Context overflow: prompt too large for the model. Try /reset (or /new) to start a fresh session, or use a larger-context model."
    },
    {
      "timestamp": "2026-02-20T10:16:45Z",
      "type": "executed",
      "taskId": "capture-1079",
      "message": "Autonomous writing sprint: Turn training requests into measurable capability outcomes: Autonomous blog task seeded and queued for OpenClaw."
    },
    {
      "timestamp": "2026-02-20T10:15:38Z",
      "type": "executed",
      "taskId": "capture-1078",
      "message": "Autonomous writing sprint: Turn training requests into measurable capability outcomes: Delegated via OpenClaw SSH (status=completed, task_id=9139b911-4b07-409c-83dd-35ea10eeea1b): Context overflow: prompt too large for the model. Try /reset (or /new) to start a fresh session, or use a larger-context model."
    },
    {
      "timestamp": "2026-02-20T10:15:25Z",
      "type": "executed",
      "taskId": "capture-1078",
      "message": "Autonomous writing sprint: Turn training requests into measurable capability outcomes: Autonomous blog task seeded and queued for OpenClaw."
    },
    {
      "timestamp": "2026-02-20T10:14:33Z",
      "type": "executed",
      "taskId": "capture-1077",
      "message": "Autonomous writing sprint: Turn training requests into measurable capability outcomes: Delegated via OpenClaw SSH (status=completed, task_id=82e9e5e7-3432-4aab-83dd-b64989d98359): Context overflow: prompt too large for the model. Try /reset (or /new) to start a fresh session, or use a larger-context model."
    },
    {
      "timestamp": "2026-02-20T10:14:26Z",
      "type": "executed",
      "taskId": "capture-1077",
      "message": "Autonomous writing sprint: Turn training requests into measurable capability outcomes: Autonomous blog task seeded and queued for OpenClaw."
    },
    {
      "timestamp": "2026-02-20T10:13:31Z",
      "type": "executed",
      "taskId": "capture-1076",
      "message": "Autonomous writing sprint: Turn training requests into measurable capability outcomes: Delegated via OpenClaw SSH (status=completed, task_id=7754c0c6-2301-433f-a7bb-e76da3febb84): Context overflow: prompt too large for the model. Try /reset (or /new) to start a fresh session, or use a larger-context model."
    },
    {
      "timestamp": "2026-02-20T10:13:23Z",
      "type": "executed",
      "taskId": "capture-1076",
      "message": "Autonomous writing sprint: Turn training requests into measurable capability outcomes: Autonomous blog task seeded and queued for OpenClaw."
    },
    {
      "timestamp": "2026-02-20T10:12:31Z",
      "type": "executed",
      "taskId": "capture-1075",
      "message": "Autonomous writing sprint: Turn training requests into measurable capability outcomes: Delegated via OpenClaw SSH (status=completed, task_id=4007b8a7-50c6-431a-b3f1-1e1ccdaedfc1): Context overflow: prompt too large for the model. Try /reset (or /new) to start a fresh session, or use a larger-context model."
    },
    {
      "timestamp": "2026-02-20T10:12:23Z",
      "type": "executed",
      "taskId": "capture-1075",
      "message": "Autonomous writing sprint: Turn training requests into measurable capability outcomes: Autonomous blog task seeded and queued for OpenClaw."
    },
    {
      "timestamp": "2026-02-20T10:11:31Z",
      "type": "executed",
      "taskId": "capture-1074",
      "message": "Design learning for decision quality, not completion rates: Delegated via OpenClaw SSH (status=completed, task_id=35de1a2a-e2ee-4b39-bc4f-ebc0333e43d7): Context overflow: prompt too large for the model. Try /reset (or /new) to start a fresh session, or use a larger-context model."
    },
    {
      "timestamp": "2026-02-20T10:11:24Z",
      "type": "executed",
      "taskId": "capture-1074",
      "message": "Autonomous writing sprint: Design learning for decision quality, not completion rates: Autonomous blog task seeded and queued for OpenClaw."
    },
    {
      "timestamp": "2026-02-20T10:06:28Z",
      "type": "executed",
      "taskId": "capture-1073",
      "message": "Autonomous writing sprint: Help cross functional teams learn faster through shared project re...: Delegated via OpenClaw SSH (status=completed, task_id=edf57bfe-a628-48ad-86a9-9a225607f241): Context overflow: prompt too large for the model. Try /reset (or /new) to start a fresh session, or use a larger-context model."
    },
    {
      "timestamp": "2026-02-20T10:06:09Z",
      "type": "executed",
      "taskId": "capture-1073",
      "message": "Autonomous writing sprint: Help cross functional teams learn faster through shared project retrospectives: Autonomous blog task seeded and queued for OpenClaw."
    },
    {
      "timestamp": "2026-02-20T10:05:31Z",
      "type": "executed",
      "taskId": "capture-1072",
      "message": "Autonomous writing sprint: Help cross functional teams learn faster through shared project re...: Delegated via OpenClaw SSH (status=completed, task_id=b8a73d86-7f54-4d67-8386-806910d56eeb): Context overflow: prompt too large for the model. Try /reset (or /new) to start a fresh session, or use a larger-context model."
    },
    {
      "timestamp": "2026-02-20T10:05:20Z",
      "type": "executed",
      "taskId": "capture-1072",
      "message": "Autonomous writing sprint: Help cross functional teams learn faster through shared project retrospectives: Autonomous blog task seeded and queued for OpenClaw."
    },
    {
      "timestamp": "2026-02-20T10:05:18Z",
      "type": "executed",
      "taskId": "capture-1071",
      "message": "Autonomous writing sprint: Help cross functional teams learn faster through shared project re...: Delegated via OpenClaw SSH (status=completed, task_id=0cf694a5-c82e-4047-94ba-9da4cadfdd6a): Context overflow: prompt too large for the model. Try /reset (or /new) to start a fresh session, or use a larger-context model."
    },
    {
      "timestamp": "2026-02-20T10:05:12Z",
      "type": "executed",
      "taskId": "capture-1071",
      "message": "Autonomous writing sprint: Help cross functional teams learn faster through shared project retrospectives: Autonomous blog task seeded and queued for OpenClaw."
    },
    {
      "timestamp": "2026-02-20T09:59:50Z",
      "type": "executed",
      "taskId": "capture-1070",
      "message": "Autonomous writing sprint: Use reflective debriefs after projects to strengthen learning tran...: Delegated via OpenClaw SSH (status=completed, task_id=608d53c4-fe67-4141-bc8b-b00d7d78a10b): # Use reflective debriefs after projects to strengthen learning transfer\n\nLearning disappears when feedback stays in the classroom. You implement brilliant programs yet teams show no visible change in their day-to-day work. I have watched countless LxD initiatives where post-training surveys showed perfect satisfaction scores yet the actual behavior on the floor never shifted. The gap between learning and living becomes permanent.\n\nTeams absorb new concepts but struggle to apply them because feedback feels ad-hoc and inconsistent. They complete training programs with enthusiastic participants yet watch weeks later as nothing changes. The learning dies because there is no ritual that forces people to practice and get feedback.\n\nReflective debriefs turn learning into visible team behavior by creating structured opportunities to apply new skills in real contexts. When feedback happens during work rather than after training you surface immediate insights about what worked and what needs adjustment. The moments people pause and think about what to do next are the ones that actually stick.\n\nWhat would your team look like if they could make confident decisions before the playbook gave them the answer?\n\nTry giving your new hire a messy real-world scenario to navigate without the full script. See what choices they make and what questions they ask. That data reveals what they already know and what needs more time to sink in.\n\n1. ATD research on learning measurement: https://www.td.org/research-resources/research-brief/learning-measurement-research\n2. Harvard Business Review on decision quality: https://hbr.org/2023/11/what-makes-a-decision-high-quality\n3. MIT Sloan research on applied learning: https://learning.mit.edu/research/topics/deep-learning/\n4. Deloitte talent development insights: https://www2.deloitte.com/insights/topics/talent-hr/learning-and-development-trends.html"
    },
    {
      "timestamp": "2026-02-20T09:59:02Z",
      "type": "executed",
      "taskId": "capture-1070",
      "message": "Autonomous writing sprint: Use reflective debriefs after projects to strengthen learning transfer: Autonomous blog task seeded and queued for OpenClaw."
    },
    {
      "timestamp": "2026-02-20T09:57:48Z",
      "type": "executed",
      "taskId": "capture-1069",
      "message": "Autonomous writing sprint: Use reflective debriefs after projects to strengthen learning tran...: Delegated via OpenClaw SSH (status=completed, task_id=3ca555ee-c429-4909-9015-5bf89b22ecd8): Unhandled stop reason: network_error"
    },
    {
      "timestamp": "2026-02-20T09:57:43Z",
      "type": "executed",
      "taskId": "capture-1069",
      "message": "Autonomous writing sprint: Use reflective debriefs after projects to strengthen learning transfer: Autonomous blog task seeded and queued for OpenClaw."
    },
    {
      "timestamp": "2026-02-20T09:56:27Z",
      "type": "executed",
      "taskId": "capture-1068",
      "message": "Create L&D reviews that focus on behavior shifts not completion dashboards: Delegated via OpenClaw SSH (status=completed, task_id=7c454c46-e6d7-4e7d-be4a-52a8756d9ef2): Unhandled stop reason: network_error"
    },
    {
      "timestamp": "2026-02-20T09:53:44Z",
      "type": "executed",
      "taskId": "capture-1068",
      "message": "Autonomous writing sprint: Create L&D reviews that focus on behavior shifts not completion dashboards: Autonomous blog task seeded and queued for OpenClaw."
    },
    {
      "timestamp": "2026-02-20T09:51:40Z",
      "type": "executed",
      "taskId": "capture-1067",
      "message": "Improve judgment without adding course fatigue: Delegated via OpenClaw SSH (status=completed, task_id=d41401fd-f919-46ec-8fc9-e1b836add48e): # Use scenario based practice to improve judgment without adding course fatigue\n\nTraining often fails because people memorize procedures but cannot apply them when situations change. They respond correctly to familiar scenarios but freeze when faced with something they have not explicitly been told to do. That disconnect creates confusion in real moments when things go wrong.\n\nI worked with a product team that struggled with decisions until they built regular feedback loops into their sprint retrospectives. Each sprint ended with a structured check-in that surfaced what worked and what needed adjustment. Their error rate dropped and customer complaints decreased. The key was asking teams to describe one decision they handled differently after a learning session, then connecting that observation to their next sprint review.\n\nScenario based practice builds judgment without adding course fatigue. Instead of waiting for formal reviews, teams implement short weekly check-ins where people share what they applied and what worked. These moments happen during work, not after training. The moments they pause and think about what to do next are the ones that actually stick.\n\nWhat would your team look like if they could make confident decisions before the playbook gave them the answer?\n\nTry giving your team a messy real-world scenario to navigate without the full script. See what choices they make and what questions they ask. That data reveals what they already know and what needs more time to sink in.\n\n1. ATD research on onboarding effectiveness: https://www.td.org/research-resources/research-brief/onboarding-effectiveness-research\n2. Harvard Business Review on decision-making skills: https://hbr.org/2024/01/building-decision-competence\n3. MIT Sloan learning research: https://learning.mit.edu/research/topics/deep-learning/\n4. Deloitte research on talent development: https://www2.deloitte.com/insights/topics/talent-hr/learning-and-development-trends.html"
    },
    {
      "timestamp": "2026-02-20T09:51:20Z",
      "type": "executed",
      "taskId": "capture-1067",
      "message": "Autonomous writing sprint: Use scenario based practice to improve judgment without adding course fatigue: Autonomous blog task seeded and queued for OpenClaw."
    },
    {
      "timestamp": "2026-02-20T09:49:34Z",
      "type": "executed",
      "taskId": "capture-1066",
      "message": "Improve judgment without adding course fatigue: Delegated via OpenClaw SSH (status=completed, task_id=6a40e7ce-d728-4678-9603-bf8b6a280264): I need to create a publish-ready blog article with the exact title \"Use scenario based practice to improve judgment without adding course fatigue\" with 180-300 words, no duplicates, and 3-4 diverse references."
    },
    {
      "timestamp": "2026-02-20T09:48:33Z",
      "type": "executed",
      "taskId": "capture-1066",
      "message": "Autonomous writing sprint: Use scenario based practice to improve judgment without adding course fatigue: Autonomous blog task seeded and queued for OpenClaw."
    },
    {
      "timestamp": "2026-02-20T09:47:38Z",
      "type": "executed",
      "taskId": "capture-1065",
      "message": "Improve judgment without adding course fatigue: Delegated via OpenClaw SSH (status=completed, task_id=8e5bb7b9-95dc-4329-a4cc-cba6afa1bd8c): Context overflow: prompt too large for the model. Try /reset (or /new) to start a fresh session, or use a larger-context model."
    },
    {
      "timestamp": "2026-02-20T09:47:31Z",
      "type": "executed",
      "taskId": "capture-1065",
      "message": "Autonomous writing sprint: Use scenario based practice to improve judgment without adding course fatigue: Autonomous blog task seeded and queued for OpenClaw."
    },
    {
      "timestamp": "2026-02-20T09:46:36Z",
      "type": "executed",
      "taskId": "capture-1064",
      "message": "Autonomous writing sprint: Coach managers to run better learning conversations in weekly one...: Delegated via OpenClaw SSH (status=completed, task_id=728714c8-2b03-4355-a27a-7ee761be562e): Context overflow: prompt too large for the model. Try /reset (or /new) to start a fresh session, or use a larger-context model."
    },
    {
      "timestamp": "2026-02-20T09:46:29Z",
      "type": "executed",
      "taskId": "capture-1064",
      "message": "Autonomous writing sprint: Coach managers to run better learning conversations in weekly one on ones: Autonomous blog task seeded and queued for OpenClaw."
    },
    {
      "timestamp": "2026-02-20T09:45:34Z",
      "type": "executed",
      "taskId": "capture-1063",
      "message": "Autonomous writing sprint: Turn training requests into measurable capability outcomes: Delegated via OpenClaw SSH (status=completed, task_id=1cc7cc23-0317-48b7-9de5-11751f1b0daf): Context overflow: prompt too large for the model. Try /reset (or /new) to start a fresh session, or use a larger-context model."
    },
    {
      "timestamp": "2026-02-20T09:45:27Z",
      "type": "executed",
      "taskId": "capture-1063",
      "message": "Autonomous writing sprint: Turn training requests into measurable capability outcomes: Autonomous blog task seeded and queued for OpenClaw."
    },
    {
      "timestamp": "2026-02-20T09:44:32Z",
      "type": "executed",
      "taskId": "capture-1062",
      "message": "Autonomous writing sprint: Turn training requests into measurable capability outcomes: Delegated via OpenClaw SSH (status=completed, task_id=943926b5-e5d0-46a9-bb68-00cdc52eb0d8): Context overflow: prompt too large for the model. Try /reset (or /new) to start a fresh session, or use a larger-context model."
    },
    {
      "timestamp": "2026-02-20T09:44:26Z",
      "type": "executed",
      "taskId": "capture-1062",
      "message": "Autonomous writing sprint: Turn training requests into measurable capability outcomes: Autonomous blog task seeded and queued for OpenClaw."
    },
    {
      "timestamp": "2026-02-20T09:43:23Z",
      "type": "executed",
      "taskId": "capture-1061",
      "message": "Autonomous writing sprint: Turn training requests into measurable capability outcomes: Delegated via OpenClaw SSH (status=completed, task_id=f9eb6b0c-4b87-47a5-8be3-581999ef907a): Context overflow: prompt too large for the model. Try /reset (or /new) to start a fresh session, or use a larger-context model."
    },
    {
      "timestamp": "2026-02-20T09:39:04Z",
      "type": "executed",
      "taskId": "capture-1061",
      "message": "Autonomous writing sprint: Turn training requests into measurable capability outcomes: Autonomous blog task seeded and queued for OpenClaw."
    },
    {
      "timestamp": "2026-02-20T09:33:53Z",
      "type": "executed",
      "taskId": "capture-1060",
      "message": "Autonomous writing sprint: Turn training requests into measurable capability outcomes: Delegated via OpenClaw SSH (status=completed, task_id=800a9d03-7303-4005-a331-36fb3c0d8776): Reviewing and optimizing article for publication"
    },
    {
      "timestamp": "2026-02-20T09:33:02Z",
      "type": "executed",
      "taskId": "capture-1060",
      "message": "Autonomous writing sprint: Turn training requests into measurable capability outcomes: Autonomous blog task seeded and queued for OpenClaw."
    },
    {
      "timestamp": "2026-02-20T09:31:05Z",
      "type": "executed",
      "taskId": "capture-1059",
      "message": "Autonomous writing sprint: Turn training requests into measurable capability outcomes: Delegated via OpenClaw SSH (status=completed, task_id=f956ed84-541a-4c88-963d-740288f1fa07): Executing blog writing workflow for training requests topic"
    },
    {
      "timestamp": "2026-02-20T09:29:53Z",
      "type": "executed",
      "taskId": "capture-1059",
      "message": "Autonomous writing sprint: Turn training requests into measurable capability outcomes: Autonomous blog task seeded and queued for OpenClaw."
    }
  ],
  "blogDashboard": {
    "updatedAt": "2026-02-20T11:56:04Z",
    "site": {
      "name": "Shreyas Korad - Writing",
      "url": "https://shreyaskorad.github.io/personal-website",
      "repo_hint": "/Users/shreyas/Documents/New project/.tmp/personal-website-ops-clean",
      "posts_path": "posts",
      "writing_index_path": "writing.html",
      "publish_script": "scripts/publish_post.py",
      "style_rules_path": "blog-writing-rules.md",
      "primary_topics": [
        "L&D",
        "gamification",
        "data",
        "LXD",
        "AI"
      ]
    },
    "execution": {
      "subagent_strategy": "serialized",
      "effective_parallelism": 1,
      "global_wip_note": "OpenClaw queue remains WIP=1 at orchestrator level."
    },
    "agents": [
      {
        "id": "topic-scout",
        "role": "Topic Scout",
        "goal": "Identify high-upside topics tied to L&D, gamification, data, LXD, and AI.",
        "output": "Prioritized topic slate with thesis, audience intent, and ranking opportunity."
      },
      {
        "id": "serp-keyword",
        "role": "Keyword and SERP Analyst",
        "goal": "Map keyword clusters, search intent, and competitor coverage gaps.",
        "output": "Primary keyword, supporting entities, SERP gap notes, and internal-link targets."
      },
      {
        "id": "brief-architect",
        "role": "Brief Architect",
        "goal": "Convert strategy into a clear brief and outline with unique angle.",
        "output": "Approved brief with section plan, CTA, and evidence requirements."
      },
      {
        "id": "research-analyst",
        "role": "Research Analyst",
        "goal": "Gather credible source material and practical examples.",
        "output": "Source-backed notes, claims table, and references for each major section."
      },
      {
        "id": "writer",
        "role": "Writer",
        "goal": "Draft publishable post aligned with site voice and audience needs.",
        "output": "Complete draft post in site format."
      },
      {
        "id": "seo-optimizer",
        "role": "Reader intent optimizer",
        "goal": "Keep title, framing, and examples aligned to practical reader intent.",
        "output": "Clear title/excerpt/heading refinements and relevance checks."
      },
      {
        "id": "editor",
        "role": "Editor",
        "goal": "Improve clarity, authority, and readability while preserving intent.",
        "output": "Final edited copy with quality notes and resolved issues."
      },
      {
        "id": "refresh-planner",
        "role": "Refresh Planner",
        "goal": "Define update cadence to protect rankings and freshness.",
        "output": "Post-publication refresh plan with triggers and review cadence."
      },
      {
        "id": "publishing-qa",
        "role": "Publishing QA",
        "goal": "Publish and verify the post is live and correctly indexed.",
        "output": "Publish proof with URL, timestamp, and pass/fail checklist."
      }
    ],
    "publishOwner": "Publishing QA",
    "analytics": {
      "status": "ok",
      "asOf": "2026-02-20T11:56:08Z",
      "lookbackDays": 28,
      "summary": {
        "users": 35,
        "sessions": 137,
        "engagedSessions": 87,
        "engagementRatePct": 63.5,
        "avgSessionDurationSec": 674.6,
        "pageViewsPerSession": 5.72,
        "vsPrevious": {
          "usersPct": null,
          "sessionsPct": null
        }
      },
      "channels": [
        {
          "channel": "Direct",
          "sessions": 126,
          "users": 24,
          "sessionShare": 92.0
        },
        {
          "channel": "Organic Search",
          "sessions": 11,
          "users": 11,
          "sessionShare": 8.0
        }
      ],
      "topPosts": [
        {
          "path": "/writing.html",
          "pageviews": 346,
          "sessions": 92,
          "engagementRatePct": 88.0,
          "avgSessionDurationSec": 424.6
        },
        {
          "path": "/posts/publishing-without-wordpress.html",
          "pageviews": 16,
          "sessions": 16,
          "engagementRatePct": 93.8,
          "avgSessionDurationSec": 24.2
        },
        {
          "path": "/posts/make-learning-evidence-useful-for-business-reviews-without-heavy-reporting-overhead.html",
          "pageviews": 13,
          "sessions": 4,
          "engagementRatePct": 100.0,
          "avgSessionDurationSec": 147.4
        },
        {
          "path": "/posts/if-everyone-is-losing-jobs-who-pays-for-ai-infrastructure.html",
          "pageviews": 11,
          "sessions": 6,
          "engagementRatePct": 83.3,
          "avgSessionDurationSec": 655.5
        },
        {
          "path": "/posts/use-learning-data-to-guide-daily-design-decisions-not-just-reports.html",
          "pageviews": 10,
          "sessions": 5,
          "engagementRatePct": 100.0,
          "avgSessionDurationSec": 221.1
        },
        {
          "path": "/posts/accelerando-ld.html",
          "pageviews": 7,
          "sessions": 3,
          "engagementRatePct": 100.0,
          "avgSessionDurationSec": 227.3
        },
        {
          "path": "/posts/ai-powered-learning-playbooks-for-product-teams.html",
          "pageviews": 7,
          "sessions": 4,
          "engagementRatePct": 100.0,
          "avgSessionDurationSec": 597.2
        },
        {
          "path": "/posts/design-decision-quality-training-that-builds-practical-judgment-instead-of-compliance.html",
          "pageviews": 6,
          "sessions": 5,
          "engagementRatePct": 100.0,
          "avgSessionDurationSec": 229.4
        }
      ],
      "insights": [
        "Organic Search share is only 8.0%, which suggests discoverability is still weak.",
        "Traffic is concentrated: the top post contributes 83.2% of views within top content."
      ],
      "nextActions": [
        "Preserve the current narrative style and expand on topics that already show strong engagement.",
        "Double down on your top-performing themes by publishing one follow-up post per week linked from high-traffic articles.",
        "Add fresh internal links from /writing.html to newer posts so authority and traffic flow across the portfolio."
      ],
      "error": "",
      "cache": {
        "hit": false,
        "fetchedAt": "2026-02-20T11:56:08Z"
      }
    },
    "taskStats": {
      "total": 80,
      "completed": 9,
      "queued": 0,
      "blocked": 6,
      "byStatus": {
        "failed": 6,
        "cancelled": 65,
        "completed": 9
      }
    },
    "recentTasks": [
      {
        "id": "openclaw-1612",
        "title": "Design learning for decision quality, not completion rates",
        "status": "failed",
        "updated_at": "2026-02-20T11:56:03Z",
        "next_steps": "Rewrite required before publish. Violations: duplicate title against published post",
        "blockers": "Publish quality gate failed."
      },
      {
        "id": "openclaw-1611",
        "title": "Design learning for decision quality, not completion rates",
        "status": "failed",
        "updated_at": "2026-02-20T11:54:39Z",
        "next_steps": "Rewrite required before publish. Violations: duplicate title against published post",
        "blockers": "Publish quality gate failed."
      },
      {
        "id": "openclaw-1610",
        "title": "Design learning for decision quality, not completion rates",
        "status": "failed",
        "updated_at": "2026-02-20T11:53:12Z",
        "next_steps": "Rewrite required before publish. Violations: duplicate title against published post",
        "blockers": "Publish quality gate failed."
      },
      {
        "id": "openclaw-1609",
        "title": "Learning transfer field note for workplace teams 20260220",
        "status": "failed",
        "updated_at": "2026-02-20T11:52:25Z",
        "next_steps": "Check OPENCLAW_SSH_HOST and OpenClaw runtime on Mac mini.",
        "blockers": "OpenClaw SSH execution failed."
      },
      {
        "id": "openclaw-1608",
        "title": "Learning transfer field note for workplace teams 20260220",
        "status": "failed",
        "updated_at": "2026-02-20T11:51:14Z",
        "next_steps": "Rewrite required before publish. Violations: duplicate title against published post",
        "blockers": "Publish quality gate failed."
      },
      {
        "id": "openclaw-1607",
        "title": "Learning transfer field note for workplace teams 20260220",
        "status": "failed",
        "updated_at": "2026-02-20T11:49:48Z",
        "next_steps": "Rewrite required before publish. Violations: duplicate title against published post",
        "blockers": "Publish quality gate failed."
      },
      {
        "id": "openclaw-1606",
        "title": "Learning transfer field note for workplace teams 20260220",
        "status": "cancelled",
        "updated_at": "2026-02-20T11:55:38Z",
        "next_steps": "Auto-requeued by autonomous mode (attempt 2/4) via inbox item #2230.",
        "blockers": ""
      },
      {
        "id": "openclaw-1605",
        "title": "Learning transfer field note for workplace teams 20260220",
        "status": "cancelled",
        "updated_at": "2026-02-20T11:54:12Z",
        "next_steps": "Auto-requeued by autonomous mode (attempt 2/4) via inbox item #2229.",
        "blockers": ""
      },
      {
        "id": "openclaw-1604",
        "title": "Learning transfer field note for workplace teams 20260220",
        "status": "cancelled",
        "updated_at": "2026-02-20T11:54:12Z",
        "next_steps": "Auto-cancelled by autonomous mode after retry limit reached; capture is preserved for manual review if needed.",
        "blockers": ""
      },
      {
        "id": "openclaw-1603",
        "title": "Improve judgment without adding course fatigue",
        "status": "completed",
        "updated_at": "2026-02-20T11:43:59Z",
        "next_steps": "",
        "blockers": ""
      },
      {
        "id": "openclaw-1602",
        "title": "Create L&D reviews that focus on behavior shifts not completion dashboards",
        "status": "cancelled",
        "updated_at": "2026-02-20T11:50:48Z",
        "next_steps": "Auto-requeued by autonomous mode (attempt 3/4) via inbox item #2213.",
        "blockers": ""
      },
      {
        "id": "openclaw-1601",
        "title": "Use reflective debriefs after projects to strengthen learning transfer",
        "status": "cancelled",
        "updated_at": "2026-02-20T11:52:13Z",
        "next_steps": "Auto-requeued by autonomous mode (attempt 2/4) via inbox item #2218.",
        "blockers": ""
      },
      {
        "id": "openclaw-1600",
        "title": "Use this exact article title: Coach managers to run better learning conversations in weekly o...",
        "status": "cancelled",
        "updated_at": "2026-02-20T11:45:29Z",
        "next_steps": "Auto-requeued by autonomous mode (attempt 1/4) via inbox item #1915.",
        "blockers": ""
      },
      {
        "id": "openclaw-1599",
        "title": "Autonomous writing sprint: Turn training requests into measurable capability outcomes",
        "status": "cancelled",
        "updated_at": "2026-02-20T11:52:13Z",
        "next_steps": "Auto-requeued by autonomous mode (attempt 1/4) via inbox item #2219.",
        "blockers": ""
      },
      {
        "id": "openclaw-1598",
        "title": "Autonomous writing sprint: Turn training requests into measurable capability outcomes",
        "status": "cancelled",
        "updated_at": "2026-02-20T11:52:13Z",
        "next_steps": "Auto-requeued by autonomous mode (attempt 1/4) via inbox item #2220.",
        "blockers": ""
      },
      {
        "id": "openclaw-1597",
        "title": "Autonomous writing sprint: Turn training requests into measurable capability outcomes",
        "status": "cancelled",
        "updated_at": "2026-02-20T11:52:13Z",
        "next_steps": "Auto-requeued by autonomous mode (attempt 1/4) via inbox item #2221.",
        "blockers": ""
      },
      {
        "id": "openclaw-1596",
        "title": "Autonomous writing sprint: Turn training requests into measurable capability outcomes",
        "status": "cancelled",
        "updated_at": "2026-02-20T11:52:13Z",
        "next_steps": "Auto-requeued by autonomous mode (attempt 1/4) via inbox item #2222.",
        "blockers": ""
      },
      {
        "id": "openclaw-1595",
        "title": "Autonomous writing sprint: Turn training requests into measurable capability outcomes",
        "status": "cancelled",
        "updated_at": "2026-02-20T11:52:13Z",
        "next_steps": "Auto-requeued by autonomous mode (attempt 1/4) via inbox item #2223.",
        "blockers": ""
      },
      {
        "id": "openclaw-1594",
        "title": "Autonomous writing sprint: Turn training requests into measurable capability outcomes",
        "status": "cancelled",
        "updated_at": "2026-02-20T11:52:13Z",
        "next_steps": "Auto-requeued by autonomous mode (attempt 1/4) via inbox item #2224.",
        "blockers": ""
      },
      {
        "id": "openclaw-1593",
        "title": "Autonomous writing sprint: Turn training requests into measurable capability outcomes",
        "status": "completed",
        "updated_at": "2026-02-20T10:12:31Z",
        "next_steps": "",
        "blockers": ""
      }
    ],
    "teamMemory": {
      "count": 25,
      "recent": [
        {
          "id": 1740,
          "created_at": "2026-02-20T11:56:03Z",
          "capture_id": 649,
          "openclaw_row_id": 1612,
          "source": "openclaw_ssh",
          "task_title": "Design learning for decision quality, not completion rates",
          "agent_id": "supervisor",
          "agent_role": "Supervisor",
          "note": "Context overflow: prompt too large for the model. Try /reset (or /new) to start a fresh session, or use a larger-context model.",
          "action_hint": "",
          "handoff_to": ""
        },
        {
          "id": 1739,
          "created_at": "2026-02-20T11:54:38Z",
          "capture_id": 647,
          "openclaw_row_id": 1611,
          "source": "openclaw_ssh",
          "task_title": "Design learning for decision quality, not completion rates",
          "agent_id": "supervisor",
          "agent_role": "Supervisor",
          "note": "Context overflow: prompt too large for the model. Try /reset (or /new) to start a fresh session, or use a larger-context model.",
          "action_hint": "",
          "handoff_to": ""
        },
        {
          "id": 1738,
          "created_at": "2026-02-20T11:53:12Z",
          "capture_id": 645,
          "openclaw_row_id": 1610,
          "source": "openclaw_ssh",
          "task_title": "Design learning for decision quality, not completion rates",
          "agent_id": "supervisor",
          "agent_role": "Supervisor",
          "note": "Context overflow: prompt too large for the model. Try /reset (or /new) to start a fresh session, or use a larger-context model.",
          "action_hint": "",
          "handoff_to": ""
        },
        {
          "id": 1737,
          "created_at": "2026-02-20T11:51:13Z",
          "capture_id": 643,
          "openclaw_row_id": 1608,
          "source": "openclaw_ssh",
          "task_title": "Learning transfer field note for workplace teams 20260220",
          "agent_id": "supervisor",
          "agent_role": "Supervisor",
          "note": "Context overflow: prompt too large for the model. Try /reset (or /new) to start a fresh session, or use a larger-context model.",
          "action_hint": "",
          "handoff_to": ""
        },
        {
          "id": 1736,
          "created_at": "2026-02-20T11:49:48Z",
          "capture_id": 648,
          "openclaw_row_id": 1607,
          "source": "openclaw_ssh",
          "task_title": "Learning transfer field note for workplace teams 20260220",
          "agent_id": "supervisor",
          "agent_role": "Supervisor",
          "note": "Context overflow: prompt too large for the model. Try /reset (or /new) to start a fresh session, or use a larger-context model.",
          "action_hint": "",
          "handoff_to": ""
        },
        {
          "id": 1735,
          "created_at": "2026-02-20T11:48:26Z",
          "capture_id": 747,
          "openclaw_row_id": 1606,
          "source": "openclaw_ssh",
          "task_title": "Learning transfer field note for workplace teams 20260220",
          "agent_id": "supervisor",
          "agent_role": "Supervisor",
          "note": "Context overflow: prompt too large for the model. Try /reset (or /new) to start a fresh session, or use a larger-context model.",
          "action_hint": "",
          "handoff_to": ""
        },
        {
          "id": 1734,
          "created_at": "2026-02-20T11:47:09Z",
          "capture_id": 835,
          "openclaw_row_id": 1605,
          "source": "openclaw_ssh",
          "task_title": "Learning transfer field note for workplace teams 20260220",
          "agent_id": "supervisor",
          "agent_role": "Supervisor",
          "note": "Context overflow: prompt too large for the model. Try /reset (or /new) to start a fresh session, or use a larger-context model.",
          "action_hint": "",
          "handoff_to": ""
        },
        {
          "id": 1733,
          "created_at": "2026-02-20T11:45:54Z",
          "capture_id": 944,
          "openclaw_row_id": 1604,
          "source": "openclaw_ssh",
          "task_title": "Learning transfer field note for workplace teams 20260220",
          "agent_id": "supervisor",
          "agent_role": "Supervisor",
          "note": "Context overflow: prompt too large for the model. Try /reset (or /new) to start a fresh session, or use a larger-context model.",
          "action_hint": "",
          "handoff_to": ""
        },
        {
          "id": 1732,
          "created_at": "2026-02-20T11:43:59Z",
          "capture_id": 1058,
          "openclaw_row_id": 1603,
          "source": "openclaw_ssh",
          "task_title": "Use scenario based practice to improve judgment without adding course fatigue",
          "agent_id": "supervisor",
          "agent_role": "Supervisor",
          "note": "Context overflow: prompt too large for the model. Try /reset (or /new) to start a fresh session, or use a larger-context model.",
          "action_hint": "",
          "handoff_to": ""
        },
        {
          "id": 1731,
          "created_at": "2026-02-20T11:43:19Z",
          "capture_id": 1057,
          "openclaw_row_id": 1602,
          "source": "openclaw_ssh",
          "task_title": "Create L&D reviews that focus on behavior shifts not completion dashboards",
          "agent_id": "supervisor",
          "agent_role": "Supervisor",
          "note": "Context overflow: prompt too large for the model. Try /reset (or /new) to start a fresh session, or use a larger-context model.",
          "action_hint": "",
          "handoff_to": ""
        },
        {
          "id": 1730,
          "created_at": "2026-02-20T11:42:11Z",
          "capture_id": 1056,
          "openclaw_row_id": 1601,
          "source": "openclaw_ssh",
          "task_title": "Use reflective debriefs after projects to strengthen learning transfer",
          "agent_id": "supervisor",
          "agent_role": "Supervisor",
          "note": "Context overflow: prompt too large for the model. Try /reset (or /new) to start a fresh session, or use a larger-context model.",
          "action_hint": "",
          "handoff_to": ""
        },
        {
          "id": 1729,
          "created_at": "2026-02-20T10:20:56Z",
          "capture_id": 1082,
          "openclaw_row_id": 1600,
          "source": "openclaw_ssh",
          "task_title": "Autonomous writing sprint: Coach managers to run better learning conversations in weekly one...",
          "agent_id": "supervisor",
          "agent_role": "Supervisor",
          "note": "Context overflow: prompt too large for the model. Try /reset (or /new) to start a fresh session, or use a larger-context model.",
          "action_hint": "",
          "handoff_to": ""
        },
        {
          "id": 1728,
          "created_at": "2026-02-20T10:19:41Z",
          "capture_id": 1081,
          "openclaw_row_id": 1599,
          "source": "openclaw_ssh",
          "task_title": "Autonomous writing sprint: Turn training requests into measurable capability outcomes",
          "agent_id": "supervisor",
          "agent_role": "Supervisor",
          "note": "Context overflow: prompt too large for the model. Try /reset (or /new) to start a fresh session, or use a larger-context model.",
          "action_hint": "",
          "handoff_to": ""
        },
        {
          "id": 1727,
          "created_at": "2026-02-20T10:18:23Z",
          "capture_id": 1080,
          "openclaw_row_id": 1598,
          "source": "openclaw_ssh",
          "task_title": "Autonomous writing sprint: Turn training requests into measurable capability outcomes",
          "agent_id": "supervisor",
          "agent_role": "Supervisor",
          "note": "Context overflow: prompt too large for the model. Try /reset (or /new) to start a fresh session, or use a larger-context model.",
          "action_hint": "",
          "handoff_to": ""
        },
        {
          "id": 1726,
          "created_at": "2026-02-20T10:17:01Z",
          "capture_id": 1079,
          "openclaw_row_id": 1597,
          "source": "openclaw_ssh",
          "task_title": "Autonomous writing sprint: Turn training requests into measurable capability outcomes",
          "agent_id": "supervisor",
          "agent_role": "Supervisor",
          "note": "Context overflow: prompt too large for the model. Try /reset (or /new) to start a fresh session, or use a larger-context model.",
          "action_hint": "",
          "handoff_to": ""
        }
      ]
    },
    "publishStats": {
      "total": 80,
      "published": 29,
      "failed": 51,
      "ignored": 0,
      "byStatus": {
        "failed": 51,
        "published": 29
      },
      "recent": [
        {
          "openclaw_row_id": 1612,
          "status": "failed",
          "url": "",
          "slug": "",
          "commit": "",
          "error": "Style rules violation: duplicate title against published post",
          "updated_at": "2026-02-20T11:56:03Z"
        },
        {
          "openclaw_row_id": 1611,
          "status": "failed",
          "url": "",
          "slug": "",
          "commit": "",
          "error": "Style rules violation: duplicate title against published post",
          "updated_at": "2026-02-20T11:54:39Z"
        },
        {
          "openclaw_row_id": 1610,
          "status": "failed",
          "url": "",
          "slug": "",
          "commit": "",
          "error": "Style rules violation: duplicate title against published post",
          "updated_at": "2026-02-20T11:53:12Z"
        },
        {
          "openclaw_row_id": 1608,
          "status": "failed",
          "url": "",
          "slug": "",
          "commit": "",
          "error": "Style rules violation: duplicate title against published post",
          "updated_at": "2026-02-20T11:51:14Z"
        },
        {
          "openclaw_row_id": 1607,
          "status": "failed",
          "url": "",
          "slug": "",
          "commit": "",
          "error": "Style rules violation: duplicate title against published post",
          "updated_at": "2026-02-20T11:49:48Z"
        },
        {
          "openclaw_row_id": 1606,
          "status": "failed",
          "url": "",
          "slug": "",
          "commit": "",
          "error": "Style rules violation: duplicate title against published post",
          "updated_at": "2026-02-20T11:48:26Z"
        },
        {
          "openclaw_row_id": 1605,
          "status": "failed",
          "url": "",
          "slug": "",
          "commit": "",
          "error": "Style rules violation: duplicate title against published post",
          "updated_at": "2026-02-20T11:47:09Z"
        },
        {
          "openclaw_row_id": 1604,
          "status": "failed",
          "url": "",
          "slug": "",
          "commit": "",
          "error": "Style rules violation: duplicate title against published post",
          "updated_at": "2026-02-20T11:45:54Z"
        },
        {
          "openclaw_row_id": 1603,
          "status": "published",
          "url": "https://shreyaskorad.github.io/personal-website/posts/improve-judgment-without-adding-course-fatigue.html",
          "slug": "improve-judgment-without-adding-course-fatigue",
          "commit": "e8377b5",
          "error": "",
          "updated_at": "2026-02-20T11:44:02Z"
        },
        {
          "openclaw_row_id": 1593,
          "status": "published",
          "url": "https://shreyaskorad.github.io/personal-website/posts/practical-learning-execution-note-for-work-teams-1593.html",
          "slug": "practical-learning-execution-note-for-work-teams-1593",
          "commit": "f6868c1",
          "error": "",
          "updated_at": "2026-02-20T11:45:08Z"
        },
        {
          "openclaw_row_id": 1592,
          "status": "published",
          "url": "https://shreyaskorad.github.io/personal-website/posts/learning-transfer-field-note-for-workplace-teams-20260220.html",
          "slug": "learning-transfer-field-note-for-workplace-teams-20260220",
          "commit": "3c241d5",
          "error": "",
          "updated_at": "2026-02-20T11:45:07Z"
        },
        {
          "openclaw_row_id": 1588,
          "status": "published",
          "url": "https://shreyaskorad.github.io/personal-website/posts/improve-decision-quality-through-practical-learning-reviews-in-february-2026.html",
          "slug": "improve-decision-quality-through-practical-learning-reviews-in-february-2026",
          "commit": "2f1ef8d",
          "error": "",
          "updated_at": "2026-02-20T11:45:05Z"
        },
        {
          "openclaw_row_id": 1587,
          "status": "published",
          "url": "https://shreyaskorad.github.io/personal-website/posts/use-reflective-debriefs-after-projects-to-strengthen-learning-t.html",
          "slug": "use-reflective-debriefs-after-projects-to-strengthen-learning-t",
          "commit": "2d8f335",
          "error": "",
          "updated_at": "2026-02-20T11:45:04Z"
        },
        {
          "openclaw_row_id": 1581,
          "status": "published",
          "url": "https://shreyaskorad.github.io/personal-website/posts/help-cross-functional-teams-learn-faster-through-shared-project-retrospectives.html",
          "slug": "help-cross-functional-teams-learn-faster-through-shared-project-retrospectives",
          "commit": "3a7566f",
          "error": "",
          "updated_at": "2026-02-20T11:45:02Z"
        },
        {
          "openclaw_row_id": 1578,
          "status": "published",
          "url": "https://shreyaskorad.github.io/personal-website/posts/create-ld-reviews-that-focus-on-behavior-shifts-not-completion-dashboards.html",
          "slug": "create-ld-reviews-that-focus-on-behavior-shifts-not-completion-dashboards",
          "commit": "74e5c4a",
          "error": "",
          "updated_at": "2026-02-20T11:45:01Z"
        },
        {
          "openclaw_row_id": 1577,
          "status": "failed",
          "url": "",
          "slug": "",
          "commit": "",
          "error": "publish_pipeline bypassed due known bad history path\nFallback publish failed: Traceback (most recent call last):\n  File \"/Users/shreyas/Documents/New project/.tmp/personal-website-ops-clean/scripts/publish_post.py\", line 1344, in <module>\n    main()\n  File \"/Users/shreyas/Documents/New project/.tmp/personal-website-ops-clean/scripts/publish_post.py\", line 1218, in main\n    raise ValueError(\"At least two sections are required\")\nValueError: At least two sections are required",
          "updated_at": "2026-02-20T11:42:18Z"
        },
        {
          "openclaw_row_id": 1576,
          "status": "failed",
          "url": "",
          "slug": "",
          "commit": "",
          "error": "Style rules violation: missing direct author voice; references do not expand source pool with new domains",
          "updated_at": "2026-02-20T11:38:43Z"
        },
        {
          "openclaw_row_id": 1574,
          "status": "failed",
          "url": "",
          "slug": "",
          "commit": "",
          "error": "Style rules violation: missing direct author voice; references do not expand source pool with new domains",
          "updated_at": "2026-02-20T11:38:43Z"
        },
        {
          "openclaw_row_id": 1572,
          "status": "failed",
          "url": "",
          "slug": "",
          "commit": "",
          "error": "Style rules violation: missing reflective question; references do not expand source pool with new domains",
          "updated_at": "2026-02-20T11:38:43Z"
        },
        {
          "openclaw_row_id": 1571,
          "status": "failed",
          "url": "",
          "slug": "",
          "commit": "",
          "error": "Style rules violation: opening and closing are not anchored to same core concept",
          "updated_at": "2026-02-20T11:42:18Z"
        }
      ]
    },
    "progress": {
      "summary": {
        "total": 120,
        "completed": 10,
        "active": 0,
        "queued": 0,
        "blocked": 6,
        "cancelled": 104
      },
      "today": {
        "completed": 3,
        "active": 0,
        "queued": 0,
        "blocked": 6,
        "published": 19
      },
      "activeTask": null,
      "lastCompletedTask": {
        "id": "openclaw-1603",
        "row_id": 1603,
        "capture_id": 1058,
        "title": "Improve judgment without adding course fatigue",
        "status": "completed",
        "updated_at": "2026-02-20T11:43:59Z",
        "next_steps": "",
        "blockers": "",
        "description": "Use this exact article title: Use scenario based practice to improve judgment without adding course fatigue. Write one publish-ready article in your authentic focus areas: L&D, gamification, LXD, data-informed learning, and practical AI use in learning. Exclude SEO/process meta content. Avoid duplicated themes and avoid previously published near-duplicate titles. Keep it practical with real workplace decisions, concrete constraints, and clear execution context. Follow strict style rules: 180-300 words, no bullets, no em dash, no blockquotes, no H2/H3 in the final body. Add a final References section with 3 credible source links from diverse domains. References are required in this run: include 3 credible links (3-4 total) and include at least one domain not used in recent posts. Do not use precise numeric claims unless cited with a verifiable source link. Avoid repeating the same core point across paragraphs; maintain natural narrative flow. Never use stock phrasing such as: 'When I work on ...', 'Practical guidance for teams:', 'Use one baseline metric, one weekly experiment ...', or 'Keep ... practical by pairing one study link ...'."
      },
      "pendingQueue": {
        "count": 20,
        "inboxCount": 20,
        "openclawQueuedCount": 0,
        "recent": [
          {
            "id": "inbox-2230",
            "capture_id": 747,
            "title": "Design learning for decision quality, not completion rates",
            "status": "pending",
            "detail": "Waiting for OpenClaw execution",
            "created_at": "2026-02-14T13:45:49Z",
            "executed_at": ""
          },
          {
            "id": "inbox-2229",
            "capture_id": 835,
            "title": "Design learning for decision quality, not completion rates",
            "status": "pending",
            "detail": "Waiting for OpenClaw execution",
            "created_at": "2026-02-16T11:39:42Z",
            "executed_at": ""
          },
          {
            "id": "inbox-2228",
            "capture_id": 1061,
            "title": "Design learning for decision quality, not completion rates",
            "status": "pending",
            "detail": "Waiting for OpenClaw execution",
            "created_at": "2026-02-20T09:39:04Z",
            "executed_at": ""
          },
          {
            "id": "inbox-2227",
            "capture_id": 1062,
            "title": "Design learning for decision quality, not completion rates",
            "status": "pending",
            "detail": "Waiting for OpenClaw execution",
            "created_at": "2026-02-20T09:44:26Z",
            "executed_at": ""
          },
          {
            "id": "inbox-2226",
            "capture_id": 1064,
            "title": "Design learning for decision quality, not completion rates",
            "status": "pending",
            "detail": "Waiting for OpenClaw execution",
            "created_at": "2026-02-20T09:46:29Z",
            "executed_at": ""
          },
          {
            "id": "inbox-2225",
            "capture_id": 1065,
            "title": "Design learning for decision quality, not completion rates",
            "status": "pending",
            "detail": "Waiting for OpenClaw execution",
            "created_at": "2026-02-20T09:47:31Z",
            "executed_at": ""
          },
          {
            "id": "inbox-2224",
            "capture_id": 1076,
            "title": "Design learning for decision quality, not completion rates",
            "status": "pending",
            "detail": "Waiting for OpenClaw execution",
            "created_at": "2026-02-20T10:13:23Z",
            "executed_at": ""
          },
          {
            "id": "inbox-2223",
            "capture_id": 1077,
            "title": "Design learning for decision quality, not completion rates",
            "status": "pending",
            "detail": "Waiting for OpenClaw execution",
            "created_at": "2026-02-20T10:14:26Z",
            "executed_at": ""
          }
        ]
      },
      "focusNote": {
        "agent_id": "supervisor",
        "created_at": "2026-02-20T11:43:59Z",
        "note": "Context overflow: prompt too large for the model. Try /reset (or /new) to start a fresh session, or use a larger-context model.",
        "action_hint": "",
        "handoff_to": ""
      },
      "bottleneck": {
        "state": "blocked",
        "reason": "Publish quality gate failed.",
        "at": "2026-02-20T11:56:03Z"
      },
      "recentIdeas": [
        {
          "id": "openclaw-1612",
          "title": "Design learning for decision quality, not completion rates",
          "status": "failed",
          "updated_at": "2026-02-20T11:56:03Z"
        },
        {
          "id": "openclaw-1611",
          "title": "Design learning for decision quality, not completion rates",
          "status": "failed",
          "updated_at": "2026-02-20T11:54:39Z"
        },
        {
          "id": "openclaw-1610",
          "title": "Design learning for decision quality, not completion rates",
          "status": "failed",
          "updated_at": "2026-02-20T11:53:12Z"
        },
        {
          "id": "openclaw-1609",
          "title": "Learning transfer field note for workplace teams 20260220",
          "status": "failed",
          "updated_at": "2026-02-20T11:52:25Z"
        },
        {
          "id": "openclaw-1608",
          "title": "Learning transfer field note for workplace teams 20260220",
          "status": "failed",
          "updated_at": "2026-02-20T11:51:14Z"
        },
        {
          "id": "openclaw-1607",
          "title": "Learning transfer field note for workplace teams 20260220",
          "status": "failed",
          "updated_at": "2026-02-20T11:49:48Z"
        },
        {
          "id": "openclaw-1606",
          "title": "Learning transfer field note for workplace teams 20260220",
          "status": "cancelled",
          "updated_at": "2026-02-20T11:55:38Z"
        },
        {
          "id": "openclaw-1605",
          "title": "Learning transfer field note for workplace teams 20260220",
          "status": "cancelled",
          "updated_at": "2026-02-20T11:54:12Z"
        },
        {
          "id": "openclaw-1604",
          "title": "Learning transfer field note for workplace teams 20260220",
          "status": "cancelled",
          "updated_at": "2026-02-20T11:54:12Z"
        },
        {
          "id": "openclaw-1603",
          "title": "Improve judgment without adding course fatigue",
          "status": "completed",
          "updated_at": "2026-02-20T11:43:59Z"
        }
      ],
      "recentOutputs": [
        {
          "id": "openclaw-1612",
          "row_id": 1612,
          "title": "Design learning for decision quality, not completion rates",
          "status": "failed",
          "url": "",
          "slug": "",
          "error": "Style rules violation: duplicate title against published post",
          "updated_at": "2026-02-20T11:56:03Z"
        },
        {
          "id": "openclaw-1611",
          "row_id": 1611,
          "title": "Design learning for decision quality, not completion rates",
          "status": "failed",
          "url": "",
          "slug": "",
          "error": "Style rules violation: duplicate title against published post",
          "updated_at": "2026-02-20T11:54:39Z"
        },
        {
          "id": "openclaw-1610",
          "row_id": 1610,
          "title": "Design learning for decision quality, not completion rates",
          "status": "failed",
          "url": "",
          "slug": "",
          "error": "Style rules violation: duplicate title against published post",
          "updated_at": "2026-02-20T11:53:12Z"
        },
        {
          "id": "openclaw-1608",
          "row_id": 1608,
          "title": "Learning transfer field note for workplace teams 20260220",
          "status": "failed",
          "url": "",
          "slug": "",
          "error": "Style rules violation: duplicate title against published post",
          "updated_at": "2026-02-20T11:51:14Z"
        },
        {
          "id": "openclaw-1607",
          "row_id": 1607,
          "title": "Learning transfer field note for workplace teams 20260220",
          "status": "failed",
          "url": "",
          "slug": "",
          "error": "Style rules violation: duplicate title against published post",
          "updated_at": "2026-02-20T11:49:48Z"
        },
        {
          "id": "openclaw-1606",
          "row_id": 1606,
          "title": "Learning transfer field note for workplace teams 20260220",
          "status": "failed",
          "url": "",
          "slug": "",
          "error": "Style rules violation: duplicate title against published post",
          "updated_at": "2026-02-20T11:48:26Z"
        },
        {
          "id": "openclaw-1605",
          "row_id": 1605,
          "title": "Learning transfer field note for workplace teams 20260220",
          "status": "failed",
          "url": "",
          "slug": "",
          "error": "Style rules violation: duplicate title against published post",
          "updated_at": "2026-02-20T11:47:09Z"
        },
        {
          "id": "openclaw-1604",
          "row_id": 1604,
          "title": "Learning transfer field note for workplace teams 20260220",
          "status": "failed",
          "url": "",
          "slug": "",
          "error": "Style rules violation: duplicate title against published post",
          "updated_at": "2026-02-20T11:45:54Z"
        },
        {
          "id": "openclaw-1603",
          "row_id": 1603,
          "title": "Improve judgment without adding course fatigue",
          "status": "published",
          "url": "https://shreyaskorad.github.io/personal-website/posts/improve-judgment-without-adding-course-fatigue.html",
          "slug": "improve-judgment-without-adding-course-fatigue",
          "error": "",
          "updated_at": "2026-02-20T11:44:02Z"
        },
        {
          "id": "openclaw-1593",
          "row_id": 1593,
          "title": "Autonomous writing sprint: Turn training requests into measurable capability outcomes",
          "status": "published",
          "url": "https://shreyaskorad.github.io/personal-website/posts/practical-learning-execution-note-for-work-teams-1593.html",
          "slug": "practical-learning-execution-note-for-work-teams-1593",
          "error": "",
          "updated_at": "2026-02-20T11:45:08Z"
        }
      ],
      "stages": {
        "focusTaskId": "openclaw-1603",
        "total": 9,
        "done": 0,
        "remaining": 9,
        "doneIds": [],
        "remainingIds": [
          "topic-scout",
          "serp-keyword",
          "brief-architect",
          "research-analyst",
          "writer",
          "seo-optimizer",
          "editor",
          "refresh-planner",
          "publishing-qa"
        ],
        "lastStageAt": "2026-02-20T11:43:59Z"
      },
      "pipeline": {
        "workerStarted": true,
        "tickInProgress": true,
        "lastStatus": "running",
        "lastReason": "background_tick",
        "lastStartedAt": "2026-02-20T11:55:24Z",
        "lastFinishedAt": "2026-02-20T11:54:39Z",
        "runtime": {
          "pending_inbox": 307,
          "active_openclaw": 0,
          "blocked_or_failed_openclaw": 6
        }
      }
    },
    "repoState": {
      "repo_hint": "/Users/shreyas/Documents/New project/.tmp/personal-website-ops-clean",
      "resolved_repo_root": "/Users/shreyas/Documents/New project/.tmp/personal-website-ops-clean",
      "candidate_health": [
        {
          "path": "/Users/shreyas/Documents/New project/.tmp/personal-website-ops-clean",
          "exists": true,
          "ok": true,
          "branch": "main...origin/main",
          "detached_head": false,
          "merge_conflicts": 0,
          "dirty_entries": 0,
          "reason": ""
        }
      ],
      "exists": true,
      "posts_path": "posts",
      "writing_index_path": "writing.html",
      "publish_script": "scripts/publish_post.py",
      "style_rules_path": "blog-writing-rules.md",
      "checks": {
        "posts_dir": true,
        "writing_index": true,
        "publish_script": true,
        "style_rules": true,
        "sitemap": true,
        "rss": true
      },
      "post_count": 50,
      "recent_posts": [
        {
          "name": "help-cross-functional-teams-learn-faster-through-shared-project-retrospectives.html",
          "updated_at": "2026-02-20T11:45:01Z"
        },
        {
          "name": "create-ld-reviews-that-focus-on-behavior-shifts-not-completion-dashboards.html",
          "updated_at": "2026-02-20T11:44:59Z"
        },
        {
          "name": "coach-managers-to-run-better-learning-conversations-in-weekly-one-on-ones.html",
          "updated_at": "2026-02-20T11:44:58Z"
        },
        {
          "name": "design-learning-for-decision-quality-not-completion-rates.html",
          "updated_at": "2026-02-20T11:44:56Z"
        },
        {
          "name": "turn-training-requests-into-measurable-capability-outcomes.html",
          "updated_at": "2026-02-20T11:44:55Z"
        },
        {
          "name": "improve-judgment-without-adding-course-fatigue.html",
          "updated_at": "2026-02-20T11:44:01Z"
        },
        {
          "name": "a-field-note-on-without-choices-that-improve-work-outcomes.html",
          "updated_at": "2026-02-20T06:49:42Z"
        },
        {
          "name": "a-practical-operating-model-for-work-and-practical-performance.html",
          "updated_at": "2026-02-20T06:49:42Z"
        },
        {
          "name": "ai-workflow-metrics-for-ld-teams.html",
          "updated_at": "2026-02-20T06:49:42Z"
        },
        {
          "name": "build-a-practical-lxd-workflow-for-small-teams-shipping-weekly.html",
          "updated_at": "2026-02-20T06:49:42Z"
        }
      ]
    }
  },
  "personalization": {
    "updatedAt": "2026-02-20T11:56:03Z",
    "metrics": {
      "reviewRequested": 1,
      "proceedCount": 0,
      "closeCount": 0
    },
    "topKeywords": [],
    "insights": [
      "FULL_AUTO_PIPELINE is active: captures auto-run through processing, execution, and ops sync."
    ]
  },
  "controls": {
    "refresh": "/api/ops/sync",
    "status_overview": "/api/status/overview",
    "captures": "/api/captures",
    "openclaw_tasks": "/api/openclaw/tasks",
    "blog_publish_backlog": "/api/blog/publish-backlog",
    "analytics": "/api/ops/analytics"
  }
}
